optisim/__init__.py
optisim/config.py
optisim/constants.py
optisim/main.py
optisim/performance.py
optisim/sensitivity.py
optisim/utils.py
optisim/model/__init__.py
optisim/model/eff_sensor.py
optisim/model/excel_methods.py
optisim/model/functions.py
optisim/model/noise.py
optisim/model/signal.py
optisim/model/spot.py
optisim/model/vis_mag.py
optisim-0.1.0.dist-info/METADATA
optisim-0.1.0.dist-info/WHEEL
optisim-0.1.0.dist-info/top_level.txt
optisim-0.1.0.dist-info/RECORD
